{"category": ["4"], "name": "view annotation at work", "language": ["SPL"], "tags": ["application development", "visualization", "reporting", "visualize", "views", "view annotation", "views example", "console", "microsoft excel", "visualization"], "url": "http://ibmstreams.github.io/streamsx.documentation/samples/spl-for-beginner/103_view_annotation_at_work_com_acme_test_ViewAnnotationAtWork_spl", "description": "This is a simple SPL application that explains the steps required to use the view annotation and then how to visualize the view annotated stream in the Streams web console. Detailed steps to view the annotated stream are shown in the commentary section of this SPL file."}