{"category": ["4"], "name": "Metrics Sink at work", "language": ["SPL"],"tags": ["metrics", "application monitoring", "custom metrics", "custom statistics"], "url": "https://github.com/IBMStreams/samples/tree/master/Examples-for-beginners/020_metrics_sink_at_work", "description": "This example shows how one can use the MetricsSink standard toolkit operator to create application-specific custom metrics that can be viewed in real-time when the application is running. Viewing of custom metrics is typically done inside Streams Explorer view of the Streams Studio or by using the capturestate option in streamtool."}
